{
  "docid": "info.bati11.wearprofile",
  "backendUrl": null,
  "details": {
    "subscriptionDetails": null,
    "tvEpisodeDetails": null,
    "albumDetails": null,
    "artistDetails": null,
    "songDetails": null,
    "tvSeasonDetails": null,
    "bookDetails": null,
    "tvShowDetails": null,
    "appDetails": {
      "everExternallyHosted": false,
      "developerEmail": "mail.bati11@gmail.com",
      "numDownloads": "100+ downloads",
      "installLocation": null,
      "packageName": "info.bati11.wearprofile",
      "appType": "APPLICATION",
      "developerWebsite": "",
      "appCategory": [],
      "certificateSet": [
        {
          "certificateHash": [
            "2UjKVmqxTdOfKXMi2fKS9unnafo"
          ]
        }
      ],
      "variesByAccount": false,
      "hasPreregistrationPromoCode": null,
      "recentChangesHtml": null,
      "uploadDate": "Sep 13, 2014",
      "developerName": "papi",
      "autoAcquireFreeAppIfHigherVersionAvailableTag": [],
      "title": null,
      "installationSize": {
        "low": 1912215,
        "high": 0,
        "unsigned": false
      },
      "installDetails": {
        "installLocation": 0,
        "dependency": {
          "skipPermissions": true,
          "minVersionCode": 5077500,
          "versionCodeMask": null,
          "packageName": "com.google.android.gms"
        },
        "targetSdkVersion": 20,
        "size": {
          "low": 1912215,
          "high": 0,
          "unsigned": false
        }
      },
      "file": [
        {
          "compressedSize": null,
          "versionCode": 2,
          "size": {
            "low": 1912215,
            "high": 0,
            "unsigned": false
          },
          "fileType": 0,
          "patchDetails": [],
          "splitId": null
        }
      ],
      "installNotes": null,
      "majorVersionNumber": null,
      "gamepadRequired": null,
      "declaresIab": null,
      "permission": [
        "android.permission.ACCESS_NETWORK_STATE",
        "android.permission.INTERNET",
        "android.permission.READ_EXTERNAL_STORAGE"
      ],
      "versionCode": 2,
      "contentRating": null,
      "certificateHash": [],
      "versionString": "1.1",
      "targetSdkVersion": 20,
      "externallyHosted": null,
      "splitId": []
    },
    "videoDetails": null,
    "magazineDetails": null
  },
  "purchaseDetailsUrl": null,
  "detailsReusable": true,
  "snippetsUrl": null,
  "productDetails": {
    "section": [
      {
        "description": [
          {
            "description": "papi",
            "image": null
          }
        ],
        "title": "Offered by"
      },
      {
        "description": [
          {
            "description": "mail.bati11@gmail.com",
            "image": null
          }
        ],
        "title": "Developer e-mail"
      }
    ],
    "title": null
  },
  "backendId": 3,
  "image": [
    {
      "palette": null,
      "citation": null,
      "backgroundColorRgb": null,
      "secureUrl": null,
      "attribution": null,
      "durationSeconds": null,
      "imageType": 1,
      "positionInSequence": 0,
      "imageUrl": "https://lh4.ggpht.com/4W_LbW_RqLwHr0cPoIYfrgQ5bPDtfSQ8b6Rf0Wm5R8ry0f_aRE99bZjoelJ5rzMMd1ye",
      "dimension": {
        "width": 499,
        "height": 410
      },
      "autogen": null,
      "deviceClass": 1,
      "fillColorRgb": null,
      "supportsFifeUrlOptions": true,
      "supportsFifeMonogramOption": null,
      "altTextLocalized": null
    },
    {
      "palette": null,
      "citation": null,
      "backgroundColorRgb": null,
      "secureUrl": null,
      "attribution": null,
      "durationSeconds": null,
      "imageType": 1,
      "positionInSequence": 1,
      "imageUrl": "https://lh6.ggpht.com/C3SVvoc4gKFb3b2Bu2aCV1AD9bXKK9EFvwBBe2Xp64-5c_PIhOSarnDgxl_BF1g3CeE",
      "dimension": {
        "width": 720,
        "height": 1280
      },
      "autogen": null,
      "deviceClass": 1,
      "fillColorRgb": null,
      "supportsFifeUrlOptions": true,
      "supportsFifeMonogramOption": null,
      "altTextLocalized": null
    },
    {
      "palette": null,
      "citation": null,
      "backgroundColorRgb": null,
      "secureUrl": null,
      "attribution": null,
      "durationSeconds": null,
      "imageType": 4,
      "positionInSequence": null,
      "imageUrl": "https://lh6.ggpht.com/TRWvZ5Jrv3AdfZy43EgYEyIPhoCUntGuc06tfIr5hyvW8FKVlTTuaZPydvSWSemWc7bD",
      "dimension": null,
      "autogen": null,
      "deviceClass": null,
      "fillColorRgb": null,
      "supportsFifeUrlOptions": true,
      "supportsFifeMonogramOption": null,
      "altTextLocalized": null
    },
    {
      "palette": null,
      "citation": null,
      "backgroundColorRgb": null,
      "secureUrl": null,
      "attribution": null,
      "durationSeconds": null,
      "imageType": 2,
      "positionInSequence": null,
      "imageUrl": "https://lh6.ggpht.com/5gxMUZQbm0wvWB5oLiqqd7x-u1rcY76swMlWEXGynzg1r4RWPA61k_8RWbNXtO0-5YNM",
      "dimension": null,
      "autogen": null,
      "deviceClass": null,
      "fillColorRgb": null,
      "supportsFifeUrlOptions": true,
      "supportsFifeMonogramOption": null,
      "altTextLocalized": null
    }
  ],
  "title": "Wear Profile",
  "serverLogsCookie": "\b\u0002\u001a6\n\u001f\u0012\u001d\n\u0017info.bati11.wearprofile\u0010\u0001\u0018\u00032\u0013\b\ufffd\ufffd\ufbd3\ufffd\ufffd\u0002\u0015Z\ufffdP\n\u001d9\ufffd\u0002\ufffd",
  "translatedDescriptionHtml": null,
  "tip": [],
  "availabileForPreregistration": null,
  "useWishlistAsPrimaryAction": null,
  "subtitle": null,
  "descriptionHtml": "Wear Profile displays your profile on the wearable device.<br><br>Enter the profile on your phone, and then sync with the wearable device.<br>You can also import profile from twitter.<br>None of the profile that has been input is uploaded to any server.<br><br>Notice that Wear Profile requires a AndroidWear device.<br><br>Ver 1.1<br>- fix crashes at read a picture in sd card on the android 4.4",
  "containerMetadata": null,
  "creator": "papi",
  "availability": {
    "availabilityProblem": [],
    "offerType": null,
    "install": [],
    "hidden": null,
    "rule": null,
    "restriction": 1,
    "perdeviceavailabilityrestriction": [],
    "availableIfOwned": true,
    "filterInfo": null,
    "ownershipInfo": null
  },
  "child": [],
  "forceShareability": null,
  "aggregateRating": {
    "oneStarRatings": {
      "low": 2,
      "high": 0,
      "unsigned": true
    },
    "fourStarRatings": {
      "low": 2,
      "high": 0,
      "unsigned": true
    },
    "commentCount": null,
    "thumbsDownCount": null,
    "threeStarRatings": {
      "low": 0,
      "high": 0,
      "unsigned": true
    },
    "bayesianMeanRating": 3.0370371341705322,
    "ratingsCount": {
      "low": 7,
      "high": 0,
      "unsigned": true
    },
    "type": 2,
    "starRating": 3.142857074737549,
    "thumbsUpCount": null,
    "twoStarRatings": {
      "low": 1,
      "high": 0,
      "unsigned": true
    },
    "fiveStarRatings": {
      "low": 2,
      "high": 0,
      "unsigned": true
    }
  },
  "docType": 1,
  "mature": false,
  "reviewsUrl": "rev?doc=info.bati11.wearprofile&n=20&o=0",
  "offer": [
    {
      "voucherTerms": null,
      "formattedAmount": "Free",
      "formattedFullAmount": null,
      "onSaleDate": null,
      "licensedOfferType": null,
      "currencyCode": "USD",
      "offerId": null,
      "onSaleDateDisplayTimeZoneOffsetMsec": null,
      "formattedName": null,
      "subscriptionContentTerms": null,
      "temporarilyFree": null,
      "buyButtonLabel": "Buy",
      "rentalTerms": null,
      "preorderFulfillmentDisplayDate": null,
      "formattedDescription": null,
      "instantPurchaseEnabled": null,
      "repeatLastPayment": null,
      "promotionLabel": [],
      "offerType": 1,
      "licenseTerms": null,
      "offerPayment": [],
      "convertedPrice": [],
      "subscriptionTerms": null,
      "preorder": null,
      "checkoutFlowRequired": false,
      "fullPriceMicros": null,
      "micros": {
        "low": 0,
        "high": 0,
        "unsigned": false
      }
    }
  ],
  "shareUrl": "https://play.google.com/store/apps/details?id=info.bati11.wearprofile",
  "backendDocid": "info.bati11.wearprofile",
  "promotionalDescription": "Wear Profile displays your profile on the wearable device.",
  "annotations": {
    "privacyPolicyUrl": null,
    "sectionPurchaseCrossSell": null,
    "sectionRateAndReview": null,
    "link": null,
    "sectionRelated": null,
    "badgeForCreator": [],
    "warning": [],
    "docBadgeContainer": [],
    "oBSOLETEReason": null,
    "creatorDoc": null,
    "suggestionReasons": null,
    "plusOneData": null,
    "overflowLink": [],
    "promotedDoc": [],
    "offerNote": null,
    "sectionCrossSell": null,
    "sectionRelatedDocType": null,
    "sectionMoreBy": null,
    "sectionSuggestForRating": null,
    "optimalDeviceClassWarning": null,
    "template": null,
    "badgeForDoc": [],
    "subscription": [],
    "sectionCoreContent": null,
    "sectionBodyOfWork": null
  },
  "detailsUrl": "details?doc=info.bati11.wearprofile"
}